Workbook

Sheet Dashboard
A1: Qure.ai Life Sciences BD CRM
A2: India-only research snapshot as of 30 Sep 2026. Verify direct contact routes and unverified roles before outreach.
D4: Leads by sector | G4: Leads by geography | J4: Pipeline stage
A5: KPI | B5: Value | D5: Sector | E5: Contacts | G5: Geography | H5: Contacts | J5: Stage | K5: Opportunities
A6: Total accounts | B6: =COUNTA(Accounts!$A$6:$A$30) -> 25 | D6: Pharma | E6: =COUNTIF(Contacts!$S$6:$S$110,D6) -> 88 | G6: Global | H6: =COUNTIF(Contacts!$G$6:$G$110,G6) -> 0 | J6: Research | K6: =COUNTIF(Opportunities!$H$6:$H$30,J6) -> 25
A7: Total contacts | B7: =COUNTA(Contacts!$A$6:$A$110) -> 100 | D7: Biotech | E7: =COUNTIF(Contacts!$S$6:$S$110,D7) -> 12 | G7: India | H7: =COUNTIF(Contacts!$G$6:$G$110,G7) -> 100 | J7: Qualified | K7: =COUNTIF(Opportunities!$H$6:$H$30,J7) -> 0
A8: High-priority leads (score ≥4.5) | B8: =COUNTIF(Contacts!$R$6:$R$110,">=4.5") -> 11 | D8: Diagnostics | E8: =COUNTIF(Contacts!$S$6:$S$110,D8) -> 0 | G8: Unverified | H8: =COUNTIF(Contacts!$G$6:$G$110,G8) -> 0 | J8: Discovery | K8: =COUNTIF(Opportunities!$H$6:$H$30,J8) -> 0
A9: Tier 1 accounts | B9: =COUNTIF(Accounts!$J$6:$J$30,"Tier 1") -> 15 | D9: Imaging & MedTech | E9: =COUNTIF(Contacts!$S$6:$S$110,D9) -> 0 | G9: Other | H9: =COUNTIF(Contacts!$G$6:$G$110,G9) -> 0 | J9: Proposal | K9: =COUNTIF(Opportunities!$H$6:$H$30,J9) -> 0
A10: Accounts with coverage | B10: =COUNTIF(Accounts!$P$6:$P$30,">0") -> 12 | D10: Digital Health | E10: =COUNTIF(Contacts!$S$6:$S$110,D10) -> 0 | J10: Negotiation | K10: =COUNTIF(Opportunities!$H$6:$H$30,J10) -> 0
A11: Overdue next steps | B11: =COUNTIF('Outreach & Activities'!$K$6:$K$35,"OVERDUE") -> 0 | D11: Clinical Research | E11: =COUNTIF(Contacts!$S$6:$S$110,D11) -> 0 | J11: Closed Won | K11: =COUNTIF(Opportunities!$H$6:$H$30,J11) -> 0
A12: Research freshness (<90 days) | B12: =COUNTIF('Research Sources'!$F$6:$F$132,">="&DATE(2026,7,2))/COUNTA('Research Sources'!$A$6:$A$132) -> 1
A13: Verified contacts | B13: =COUNTIF(Contacts!$P$6:$P$110,"Verified - official source") -> 82 | D13: Leads by seniority | G13: Leads by solution interest
D14: Seniority | E14: Contacts | G14: Solution interest | H14: Contacts
D15: C-suite | E15: =COUNTIF(Contacts!$F$6:$F$110,D15) -> 40 | G15: Clinical trials / imaging biomarkers | H15: =COUNTIF(Contacts!$L$6:$L$110,G15) -> 7
D16: EVP/SVP | E16: =COUNTIF(Contacts!$F$6:$F$110,D16) -> 39 | G16: Imaging AI integration | H16: =COUNTIF(Contacts!$L$6:$L$110,G16) -> 0
D17: VP | E17: =COUNTIF(Contacts!$F$6:$F$110,D17) -> 0 | G17: Digital health / AI platform | H17: =COUNTIF(Contacts!$L$6:$L$110,G17) -> 4
D18: Director | E18: =COUNTIF(Contacts!$F$6:$F$110,D18) -> 21 | G18: RWE / commercial evidence | H18: =COUNTIF(Contacts!$L$6:$L$110,G18) -> 89
D19: Global Head | E19: =COUNTIF(Contacts!$F$6:$F$110,D19) -> 0
D20: Business Unit Head | E20: =COUNTIF(Contacts!$F$6:$F$110,D20) -> 0

Sheet Accounts
A1: Accounts
A2: Priority Life Sciences / MedTech account universe. As of 30 Sep 2026.
A5: Account ID | B5: Company name | C5: Sector | D5: Sub-sector | E5: Headquarters | F5: Priority markets | G5: Company size / revenue band | H5: Relevant therapeutic/device focus | I5: Existing Qure.ai relevance / use case | J5: Strategic tier | K5: Account owner | L5: Relationship status | M5: Account-level opportunity hypothesis | N5: Source URL | O5: Research date | P5: Coverage score
A6: ACC-001 | B6: Sun Pharmaceutical Industries | C6: Pharma | D6: India Pharma | E6: Mumbai, India | F6: India; Emerging Markets | G6: Large / listed India | H6: Specialty, chronic care, generics | I6: Clinical evidence; imaging biomarkers | J6: Tier 1 | K6: Life Sciences BD - India | L6: Prospect | M6: India commercial scale and specialty portfolio justify evidence-generation outreach. | N6: https://sunpharma.com/board-of-directors/ | O6: 46295 | P6: =COUNTIF(Contacts!$B$6:$B$110,A6)/4 -> 3.75
A7: ACC-002 | B7: Dr. Reddy’s Laboratories | C7: Pharma | D7: India Pharma & Services | E7: Hyderabad, India | F7: India; US; EU; Emerging Markets | G7: Large / listed India | H7: Generics, biosimilars, API, services | I7: Clinical trials; RWE; digital health | J7: Tier 1 | K7: Life Sciences BD - India | L7: Prospect | M7: India and emerging-market portfolio provides clinical-development and evidence opportunities. | N7: https://api.drreddys.com/pt-pt/events/cphi-india-2025 | O7: 46295 | P7: =COUNTIF(Contacts!$B$6:$B$110,A7)/4 -> 2.5
A8: ACC-003 | B8: Cipla | C8: Pharma | D8: India Pharma | E8: Mumbai, India | F8: India; South Africa; Emerging Markets | G8: Large / listed India | H8: Respiratory, HIV, chronic therapies | I8: Digital health; RWE; access evidence | J8: Tier 1 | K8: Life Sciences BD - India | L8: Prospect | M8: Digital-health and India leadership make Cipla a priority evidence partner. | N8: https://www.cipla.com/node/713474 | O8: 46295 | P8: =COUNTIF(Contacts!$B$6:$B$110,A8)/4 -> 1.25
A9: ACC-004 | B9: Biocon | C9: Biotech | D9: Biosimilars & Biologics | E9: Bengaluru, India | F9: India; US; EU; Emerging Markets | G9: Large / listed India | H9: Biosimilars, peptides, APIs | I9: Clinical development; medical affairs | J9: Tier 1 | K9: Life Sciences BD - India | L9: Prospect | M9: Biosimilar development and global commercialization create imaging/RWE hypotheses. | N9: https://www.biocon.com/about-us/executive-committee/ | O9: 46295 | P9: =COUNTIF(Contacts!$B$6:$B$110,A9)/4 -> 3
A10: ACC-005 | B10: Lupin | C10: Pharma | D10: India Pharma | E10: Mumbai, India | F10: India; US; EU; Emerging Markets | G10: Large / listed India | H10: Chronic care, respiratory, TB, biologics | I10: Clinical development; digital health | J10: Tier 1 | K10: Life Sciences BD - India | L10: Prospect | M10: India formulations and innovation teams are high-priority targets. | N10: https://lupin.com/about-us/leadership | O10: 46295 | P10: =COUNTIF(Contacts!$B$6:$B$110,A10)/4 -> 4
A11: ACC-006 | B11: Aurobindo Pharma | C11: Pharma | D11: India Pharma | E11: Hyderabad, India | F11: India; US; EU; Emerging Markets | G11: Large / listed India | H11: Generics, biologics, vaccines, peptides | I11: Clinical development; MedTech integration | J11: Tier 1 | K11: Life Sciences BD - India | L11: Prospect | M11: Biologics and vaccine leadership are relevant to trial-imaging partnerships. | N11: https://www.aurobindo.com/about-us/management/board-of-directors | O11: 46295 | P11: =COUNTIF(Contacts!$B$6:$B$110,A11)/4 -> 2.25
A12: ACC-007 | B12: Alembic Pharmaceuticals | C12: Pharma | D12: India Pharma | E12: Vadodara, India | F12: India; US; EU | G12: Large / listed India | H12: Formulations, API | I12: Clinical development; commercial evidence | J12: Tier 2 | K12: Life Sciences BD - India | L12: Prospect | M12: India pharma account with public senior-management disclosures. | N12: https://alembicpharmaceuticals.com/shareholder-information | O12: 46295 | P12: =COUNTIF(Contacts!$B$6:$B$110,A12)/4 -> 1.5
A13: ACC-008 | B13: GSK India | C13: Pharma | D13: India Commercial & Vaccines | E13: Mumbai, India | F13: India | G13: Large / listed India affiliate | H13: Vaccines, oncology, general medicines | I13: Medical affairs; RWE; India pilots | J13: Tier 1 | K13: Life Sciences BD - India | L13: Prospect | M13: Medical and regulatory leadership can sponsor India evidence programs. | N13: https://india-pharma.gsk.com/en-in/company/board-of-directors-and-india-leadership-team/ | O13: 46295 | P13: =COUNTIF(Contacts!$B$6:$B$110,A13)/4 -> 3.5
A14: ACC-009 | B14: Zydus Lifesciences | C14: Pharma | D14: India Pharma | E14: Ahmedabad, India | F14: India; US; EU; Emerging Markets | G14: Large / listed India | H14: Vaccines, biologics, formulations | I14: Clinical development; diagnostics | J14: Tier 1 | K14: Life Sciences BD - India | L14: Prospect | M14: India innovation and vaccine platform is strategically relevant. | N14: https://www.zyduslife.com/investor/admin/uploads/14/2/2024-2025.pdf | O14: 46295 | P14: =COUNTIF(Contacts!$B$6:$B$110,A14)/4 -> 1.25
A15: ACC-010 | B15: Torrent Pharmaceuticals | C15: Pharma | D15: India Pharma | E15: Ahmedabad, India | F15: India; US; EU | G15: Large / listed India | H15: Cardiovascular, CNS, GI, diabetes | I15: RWE; commercial evidence | J15: Tier 2 | K15: Life Sciences BD - India | L15: Prospect | M15: Chronic-therapy market leadership supports RWE and commercial-evidence hypothesis. | N15: https://www.torrentpharma.com/investors/corporate-governance/board-of-directors/ | O15: 46295 | P15: =COUNTIF(Contacts!$B$6:$B$110,A15)/4 -> 0.75
A16: ACC-011 | B16: Mankind Pharma | C16: Pharma | D16: India Pharma | E16: New Delhi, India | F16: India; Emerging Markets | G16: Large / listed India | H16: Acute and chronic therapies, consumer health | I16: India evidence; commercial partnerships | J16: Tier 2 | K16: Life Sciences BD - India | L16: Prospect | M16: Large India commercial platform; senior-contact roles require verification. | N16: https://www.mankindpharma.com/about-us/board-of-directors | O16: 46295 | P16: =COUNTIF(Contacts!$B$6:$B$110,A16)/4 -> 0.75
A17: ACC-012 | B17: Emcure Pharmaceuticals | C17: Pharma | D17: India Pharma | E17: Pune, India | F17: India; US; EU; Emerging Markets | G17: Large / listed India | H17: Oncology, gynecology, cardiovascular | I17: Clinical trials; medical affairs | J17: Tier 2 | K17: Life Sciences BD - India | L17: Prospect | M17: India specialty portfolio supports clinical evidence exploration. | N17: https://www.emcure.com/about-us/leadership/ | O17: 46295 | P17: =COUNTIF(Contacts!$B$6:$B$110,A17)/4 -> 0.5
... A30: ACC-025 | B30: Narayana Health | C30: Imaging & MedTech | D30: Provider Network | E30: Bengaluru, India | F30: India | G30: Large / listed India | H30: Hospitals, oncology, cardiology | I30: Imaging AI; clinical workflow | J30: Tier 2 | K30: Strategic Partnerships | L30: Prospect | M30: Provider-network opportunity; contact research queued. | N30: https://www.narayanahealth.org/about-us/leadership | O30: 46295 | P30: =COUNTIF(Contacts!$B$6:$B$110,A30)/4 -> 0

Sheet Contacts
A1: Contacts
A2: Public professional information only. No inferred personal emails, phones, or profile URLs.
A5: Contact ID | B5: Account ID | C5: Full name | D5: Current job title | E5: Function | F5: Seniority | G5: Geography | H5: Verified public profile URL | I5: Public work email | J5: Relevance score (1–5) | K5: Buying influence | L5: Likely Qure.ai use case | M5: Personalisation / research notes | N5: Source URL | O5: Source type | P5: Verification status | Q5: Last verified date | R5: Lead score | S5: Account sector
A6: CON-001 | B6: ACC-001 | C6: Dilip Shanghvi | D6: Executive Chairman | E6: Executive Leadership | F6: C-suite | G6: India | J6: 4 | K6: Economic Buyer | L6: RWE / commercial evidence | M6: Official company leadership source reviewed; tailor outreach to India evidence, clinical development, medical affairs, or digital-health priorities. | N6: https://sunpharma.com/board-of-directors/ | O6: Official company leadership page | P6: Verified - official source | Q6: 46295 | R6: =ROUND((J6*0.7)+IF(K6="Economic Buyer",1.5,IF(K6="Champion",1.2,IF(K6="Technical Evaluator",1,0.7))),1) -> 4.3 | S6: =VLOOKUP(B6,Accounts!$A$6:$C$30,3,FALSE) -> Pharma
A7: CON-002 | B7: ACC-001 | C7: Kirti Ganorkar | D7: Managing Director | E7: Executive Leadership | F7: C-suite | G7: India | J7: 4 | K7: Economic Buyer | L7: RWE / commercial evidence | M7: Official company leadership source reviewed; tailor outreach to India evidence, clinical development, medical affairs, or digital-health priorities. | N7: https://sunpharma.com/board-of-directors/ | O7: Official company leadership page | P7: Verified - official source | Q7: 46295 | R7: =ROUND((J7*0.7)+IF(K7="Economic Buyer",1.5,IF(K7="Champion",1.2,IF(K7="Technical Evaluator",1,0.7))),1) -> 4.3 | S7: =VLOOKUP(B7,Accounts!$A$6:$C$30,3,FALSE) -> Pharma
A8: CON-003 | B8: ACC-001 | C8: Aalok Shanghvi | D8: Executive Director | E8: Corporate Development | F8: EVP/SVP | G8: India | J8: 4 | K8: Champion | L8: RWE / commercial evidence | M8: Official company leadership source reviewed; tailor outreach to India evidence, clinical development, medical affairs, or digital-health priorities. | N8: https://sunpharma.com/board-of-directors/ | O8: Official company leadership page | P8: Verified - official source | Q8: 46295 | R8: =ROUND((J8*0.7)+IF(K8="Economic Buyer",1.5,IF(K8="Champion",1.2,IF(K8="Technical Evaluator",1,0.7))),1) -> 4 | S8: =VLOOKUP(B8,Accounts!$A$6:$C$30,3,FALSE) -> Pharma
A9: CON-004 | B9: ACC-001 | C9: Vidhi Shanghvi | D9: Executive Director | E9: Commercial / Market Access | F9: EVP/SVP | G9: India | J9: 4 | K9: Champion | L9: RWE / commercial evidence | M9: Official company leadership source reviewed; tailor outreach to India evidence, clinical development, medical affairs, or digital-health priorities. | N9: https://sunpharma.com/board-of-directors/ | O9: Official company leadership page | P9: Verified - official source | Q9: 46295 | R9: =ROUND((J9*0.7)+IF(K9="Economic Buyer",1.5,IF(K9="Champion",1.2,IF(K9="Technical Evaluator",1,0.7))),1) -> 4 | S9: =VLOOKUP(B9,Accounts!$A$6:$C$30,3,FALSE) -> Pharma
A10: CON-005 | B10: ACC-001 | C10: Pawan Goenka | D10: Lead Independent Director | E10: Executive Leadership | F10: Director | G10: India | J10: 4 | K10: Economic Buyer | L10: RWE / commercial evidence | M10: Official company leadership source reviewed; tailor outreach to India evidence, clinical development, medical affairs, or digital-health priorities. | N10: https://sunpharma.com/board-of-directors/ | O10: Official company leadership page | P10: Verified - official source | Q10: 46295 | R10: =ROUND((J10*0.7)+IF(K10="Economic Buyer",1.5,IF(K10="Champion",1.2,IF(K10="Technical Evaluator",1,0.7))),1) -> 4.3 | S10: =VLOOKUP(B10,Accounts!$A$6:$C$30,3,FALSE) -> Pharma
A11: CON-006 | B11: ACC-001 | C11: Gautam Doshi | D11: Independent Director | E11: Corporate Development | F11: Director | G11: India | J11: 4 | K11: Champion | L11: RWE / commercial evidence | M11: Official company leadership source reviewed; tailor outreach to India evidence, clinical development, medical affairs, or digital-health priorities. | N11: https://sunpharma.com/board-of-directors/ | O11: Official company leadership page | P11: Verified - official source | Q11: 46295 | R11: =ROUND((J11*0.7)+IF(K11="Economic Buyer",1.5,IF(K11="Champion",1.2,IF(K11="Technical Evaluator",1,0.7))),1) -> 4 | S11: =VLOOKUP(B11,Accounts!$A$6:$C$30,3,FALSE) -> Pharma
A12: CON-007 | B12: ACC-001 | C12: Andreas Eugen Busch | D12: Independent Director | E12: R&D / Clinical Development | F12: Director | G12: India | J12: 5 | K12: Technical Evaluator | L12: Clinical trials / imaging biomarkers | M12: Official company leadership source reviewed; tailor outreach to India evidence, clinical development, medical affairs, or digital-health priorities. | N12: https://sunpharma.com/board-of-directors/ | O12: Official company leadership page | P12: Verified - official source | Q12: 46295 | R12: =ROUND((J12*0.7)+IF(K12="Economic Buyer",1.5,IF(K12="Champion",1.2,IF(K12="Technical Evaluator",1,0.7))),1) -> 4.5 | S12: =VLOOKUP(B12,Accounts!$A$6:$C$30,3,FALSE) -> Pharma
A13: CON-008 | B13: ACC-001 | C13: Rolf Hoffmann | D13: Independent Director | E13: Executive Leadership | F13: Director | G13: India | J13: 4 | K13: Economic Buyer | L13: RWE / commercial evidence | M13: Official company leadership source reviewed; tailor outreach to India evidence, clinical development, medical affairs, or digital-health priorities. | N13: https://sunpharma.com/board-of-directors/ | O13: Official company leadership page | P13: Verified - official source | Q13: 46295 | R13: =ROUND((J13*0.7)+IF(K13="Economic Buyer",1.5,IF(K13="Champion",1.2,IF(K13="Technical Evaluator",1,0.7))),1) -> 4.3 | S13: =VLOOKUP(B13,Accounts!$A$6:$C$30,3,FALSE) -> Pharma
A14: CON-009 | B14: ACC-001 | C14: Satyavati Berera | D14: Independent Director | E14: Executive Leadership | F14: Director | G14: India | J14: 4 | K14: Economic Buyer | L14: RWE / commercial evidence | M14: Official company leadership source reviewed; tailor outreach to India evidence, clinical development, medical affairs, or digital-health priorities. | N14: https://sunpharma.com/board-of-directors/ | O14: Official company leadership page | P14: Verified - official source | Q14: 46295 | R14: =ROUND((J14*0.7)+IF(K14="Economic Buyer",1.5,IF(K14="Champion",1.2,IF(K14="Technical Evaluator",1,0.7))),1) -> 4.3 | S14: =VLOOKUP(B14,Accounts!$A$6:$C$30,3,FALSE) -> Pharma
A15: CON-010 | B15: ACC-001 | C15: Kalyanasundaram Subramanian | D15: Executive Director | E15: Corporate Development | F15: EVP/SVP | G15: India | J15: 4 | K15: Champion | L15: RWE / commercial evidence | M15: Official company leadership source reviewed; tailor outreach to India evidence, clinical development, medical affairs, or digital-health priorities. | N15: https://sunpharma.com/board-of-directors/ | O15: Official company leadership page | P15: Verified - official source | Q15: 46295 | R15: =ROUND((J15*0.7)+IF(K15="Economic Buyer",1.5,IF(K15="Champion",1.2,IF(K15="Technical Evaluator",1,0.7))),1) -> 4 | S15: =VLOOKUP(B15,Accounts!$A$6:$C$30,3,FALSE) -> Pharma
A16: CON-011 | B16: ACC-001 | C16: Jayashree Satagopan | D16: Chief Financial Officer | E16: Executive Leadership | F16: C-suite | G16: India | J16: 4 | K16: Economic Buyer | L16: RWE / commercial evidence | M16: Official company leadership source reviewed; tailor outreach to India evidence, clinical development, medical affairs, or digital-health priorities. | N16: https://sunpharma.com/board-of-directors/ | O16: Official company leadership page | P16: Verified - official source | Q16: 46295 | R16: =ROUND((J16*0.7)+IF(K16="Economic Buyer",1.5,IF(K16="Champion",1.2,IF(K16="Technical Evaluator",1,0.7))),1) -> 4.3 | S16: =VLOOKUP(B16,Accounts!$A$6:$C$30,3,FALSE) -> Pharma
A17: CON-012 | B17: ACC-001 | C17: Anoop Deshpande | D17: Company Secretary & Compliance Officer | E17: Executive Leadership | F17: Director | G17: India | J17: 4 | K17: Economic Buyer | L17: RWE / commercial evidence | M17: Official company leadership source reviewed; tailor outreach to India evidence, clinical development, medical affairs, or digital-health priorities. | N17: https://sunpharma.com/board-of-directors/ | O17: Official company leadership page | P17: Verified - official source | Q17: 46295 | R17: =ROUND((J17*0.7)+IF(K17="Economic Buyer",1.5,IF(K17="Champion",1.2,IF(K17="Technical Evaluator",1,0.7))),1) -> 4.3 | S17: =VLOOKUP(B17,Accounts!$A$6:$C$30,3,FALSE) -> Pharma
... A105: CON-100 | B105: ACC-012 | C105: Namita Thapar | D105: Executive Director | E105: Commercial / Market Access | F105: EVP/SVP | G105: India | J105: 4 | K105: Champion | L105: RWE / commercial evidence | M105: Publicly known leadership record retained for research continuity. Verify current role directly on the company site before outreach. | N105: https://www.emcure.com/about-us/leadership/ | O105: Official company leadership page | P105: Unverified - recheck official source | Q105: 46295 | R105: =ROUND((J105*0.7)+IF(K105="Economic Buyer",1.5,IF(K105="Champion",1.2,IF(K105="Technical Evaluator",1,0.7))),1) -> 4 | S105: =VLOOKUP(B105,Accounts!$A$6:$C$30,3,FALSE) -> Pharma

Sheet Opportunities
A1: Opportunities
A2: All opportunity values and close dates are planning placeholders, not forecasts.
A5: Opportunity ID | B5: Account ID | C5: Contact ID | D5: Company | E5: Primary contact | F5: Use case | G5: Estimated value band | H5: Stage | I5: Probability | J5: Expected close date | K5: Competition / alternatives | L5: Key stakeholder map | M5: Next best action | N5: Risks and dependencies | O5: Activity status
A6: OPP-001 | B6: ACC-001 | C6: CON-001 | D6: Sun Pharmaceutical Industries | E6: Dilip Shanghvi | F6: Clinical evidence; imaging biomarkers | G6: ₹40L–₹1Cr | H6: Research | I6: 15 | J6: 46357 | K6: Internal build; existing data vendors | L6: Map India medical, clinical, digital and commercial stakeholders | M6: Validate India use case and request an appropriate business conversation | N6: Role verification and internal sponsorship required | O6: Planned
A7: OPP-002 | B7: ACC-002 | C7: CON-016 | D7: Dr. Reddy’s Laboratories | E7: Deepak Sapra | F7: Clinical trials; RWE; digital health | G7: ₹40L–₹1Cr | H7: Research | I7: 15 | J7: 46358 | K7: Internal build; existing data vendors | L7: Map India medical, clinical, digital and commercial stakeholders | M7: Validate India use case and request an appropriate business conversation | N7: Role verification and internal sponsorship required | O7: Planned
A8: OPP-003 | B8: ACC-003 | C8: CON-026 | D8: Cipla | E8: Achin Gupta | F8: Digital health; RWE; access evidence | G8: ₹40L–₹1Cr | H8: Research | I8: 15 | J8: 46359 | K8: Internal build; existing data vendors | L8: Map India medical, clinical, digital and commercial stakeholders | M8: Validate India use case and request an appropriate business conversation | N8: Role verification and internal sponsorship required | O8: Planned
A9: OPP-004 | B9: ACC-004 | C9: CON-031 | D9: Biocon | E9: Shreehas P Tambe | F9: Clinical development; medical affairs | G9: ₹40L–₹1Cr | H9: Research | I9: 15 | J9: 46360 | K9: Internal build; existing data vendors | L9: Map India medical, clinical, digital and commercial stakeholders | M9: Validate India use case and request an appropriate business conversation | N9: Role verification and internal sponsorship required | O9: Planned
A10: OPP-005 | B10: ACC-005 | C10: CON-043 | D10: Lupin | E10: Manju D Gupta | F10: Clinical development; digital health | G10: ₹40L–₹1Cr | H10: Research | I10: 15 | J10: 46361 | K10: Internal build; existing data vendors | L10: Map India medical, clinical, digital and commercial stakeholders | M10: Validate India use case and request an appropriate business conversation | N10: Role verification and internal sponsorship required | O10: Planned
A11: OPP-006 | B11: ACC-006 | C11: CON-059 | D11: Aurobindo Pharma | E11: Mangalam Ramasubramanian Kumar | F11: Clinical development; MedTech integration | G11: ₹40L–₹1Cr | H11: Research | I11: 15 | J11: 46362 | K11: Internal build; existing data vendors | L11: Map India medical, clinical, digital and commercial stakeholders | M11: Validate India use case and request an appropriate business conversation | N11: Role verification and internal sponsorship required | O11: Planned
A12: OPP-007 | B12: ACC-007 | C12: CON-068 | D12: Alembic Pharmaceuticals | E12: Chirayu Amin | F12: Clinical development; commercial evidence | G12: ₹10L–₹40L | H12: Research | I12: 15 | J12: 46363 | K12: Internal build; existing data vendors | L12: Map India medical, clinical, digital and commercial stakeholders | M12: Validate India use case and request an appropriate business conversation | N12: Role verification and internal sponsorship required | O12: Planned
A13: OPP-008 | B13: ACC-008 | C13: CON-074 | D13: GSK India | E13: Bhushan Akshikar | F13: Medical affairs; RWE; India pilots | G13: ₹40L–₹1Cr | H13: Research | I13: 15 | J13: 46364 | K13: Internal build; existing data vendors | L13: Map India medical, clinical, digital and commercial stakeholders | M13: Validate India use case and request an appropriate business conversation | N13: Role verification and internal sponsorship required | O13: Planned
A14: OPP-009 | B14: ACC-009 | C14: CON-088 | D14: Zydus Lifesciences | E14: Pankaj Patel | F14: Clinical development; diagnostics | G14: ₹40L–₹1Cr | H14: Research | I14: 15 | J14: 46365 | K14: Internal build; existing data vendors | L14: Map India medical, clinical, digital and commercial stakeholders | M14: Validate India use case and request an appropriate business conversation | N14: Role verification and internal sponsorship required | O14: Planned
A15: OPP-010 | B15: ACC-010 | C15: CON-093 | D15: Torrent Pharmaceuticals | E15: Samir Mehta | F15: RWE; commercial evidence | G15: ₹10L–₹40L | H15: Research | I15: 15 | J15: 46366 | K15: Internal build; existing data vendors | L15: Map India medical, clinical, digital and commercial stakeholders | M15: Validate India use case and request an appropriate business conversation | N15: Role verification and internal sponsorship required | O15: Planned
A16: OPP-011 | B16: ACC-011 | C16: CON-096 | D16: Mankind Pharma | E16: R C Juneja | F16: India evidence; commercial partnerships | G16: ₹10L–₹40L | H16: Research | I16: 15 | J16: 46367 | K16: Internal build; existing data vendors | L16: Map India medical, clinical, digital and commercial stakeholders | M16: Validate India use case and request an appropriate business conversation | N16: Role verification and internal sponsorship required | O16: Planned
A17: OPP-012 | B17: ACC-012 | C17: CON-099 | D17: Emcure Pharmaceuticals | E17: Satish Mehta | F17: Clinical trials; medical affairs | G17: ₹10L–₹40L | H17: Research | I17: 15 | J17: 46368 | K17: Internal build; existing data vendors | L17: Map India medical, clinical, digital and commercial stakeholders | M17: Validate India use case and request an appropriate business conversation | N17: Role verification and internal sponsorship required | O17: Planned
A18: OPP-013 | B18: ACC-013 | D18: Glenmark Pharmaceuticals | E18: Unassigned - contact research required | F18: Clinical development; RWE | G18: ₹10L–₹40L | H18: Research | I18: 15 | J18: 46369 | K18: Internal build; existing data vendors | L18: Map India medical, clinical, digital and commercial stakeholders | M18: Validate India use case and request an appropriate business conversation | N18: Role verification and internal sponsorship required | O18: Planned
A19: OPP-014 | B19: ACC-014 | D19: Alkem Laboratories | E19: Unassigned - contact research required | F19: Commercial evidence; RWE | G19: ₹10L–₹40L | H19: Research | I19: 15 | J19: 46370 | K19: Internal build; existing data vendors | L19: Map India medical, clinical, digital and commercial stakeholders | M19: Validate India use case and request an appropriate business conversation | N19: Role verification and internal sponsorship required | O19: Planned
A20: OPP-015 | B20: ACC-015 | D20: Intas Pharmaceuticals | E20: Unassigned - contact research required | F20: Clinical development; imaging biomarkers | G20: ₹40L–₹1Cr | H20: Research | I20: 15 | J20: 46371 | K20: Internal build; existing data vendors | L20: Map India medical, clinical, digital and commercial stakeholders | M20: Validate India use case and request an appropriate business conversation | N20: Role verification and internal sponsorship required | O20: Planned
A21: OPP-016 | B21: ACC-016 | D21: Serum Institute of India | E21: Unassigned - contact research required | F21: Clinical development; RWE | G21: ₹40L–₹1Cr | H21: Research | I21: 15 | J21: 46372 | K21: Internal build; existing data vendors | L21: Map India medical, clinical, digital and commercial stakeholders | M21: Validate India use case and request an appropriate business conversation | N21: Role verification and internal sponsorship required | O21: Planned
A22: OPP-017 | B22: ACC-017 | D22: Bharat Biotech | E22: Unassigned - contact research required | F22: Clinical development; imaging biomarkers | G22: ₹40L–₹1Cr | H22: Research | I22: 15 | J22: 46373 | K22: Internal build; existing data vendors | L22: Map India medical, clinical, digital and commercial stakeholders | M22: Validate India use case and request an appropriate business conversation | N22: Role verification and internal sponsorship required | O22: Planned
A23: OPP-018 | B23: ACC-018 | D23: Tata Medical and Diagnostics | E23: Unassigned - contact research required | F23: Diagnostics AI; clinical workflow | G23: ₹40L–₹1Cr | H23: Research | I23: 15 | J23: 46374 | K23: Internal build; existing data vendors | L23: Map India medical, clinical, digital and commercial stakeholders | M23: Validate India use case and request an appropriate business conversation | N23: Role verification and internal sponsorship required | O23: Planned
A24: OPP-019 | B24: ACC-019 | D24: Trivitron Healthcare | E24: Unassigned - contact research required | F24: AI imaging and diagnostics | G24: ₹40L–₹1Cr | H24: Research | I24: 15 | J24: 46375 | K24: Internal build; existing data vendors | L24: Map India medical, clinical, digital and commercial stakeholders | M24: Validate India use case and request an appropriate business conversation | N24: Role verification and internal sponsorship required | O24: Planned
A25: OPP-020 | B25: ACC-020 | D25: Molbio Diagnostics | E25: Unassigned - contact research required | F25: Diagnostics AI; clinical workflow | G25: ₹10L–₹40L | H25: Research | I25: 15 | J25: 46376 | K25: Internal build; existing data vendors | L25: Map India medical, clinical, digital and commercial stakeholders | M25: Validate India use case and request an appropriate business conversation | N25: Role verification and internal sponsorship required | O25: Planned
A26: OPP-021 | B26: ACC-021 | D26: HealthCare Global Enterprises | E26: Unassigned - contact research required | F26: Imaging workflow; clinical research | G26: ₹40L–₹1Cr | H26: Research | I26: 15 | J26: 46357 | K26: Internal build; existing data vendors | L26: Map India medical, clinical, digital and commercial stakeholders | M26: Validate India use case and request an appropriate business conversation | N26: Role verification and internal sponsorship required | O26: Planned
A27: OPP-022 | B27: ACC-022 | D27: Apollo Hospitals Enterprise | E27: Unassigned - contact research required | F27: Imaging AI; enterprise clinical workflow | G27: ₹40L–₹1Cr | H27: Research | I27: 15 | J27: 46358 | K27: Internal build; existing data vendors | L27: Map India medical, clinical, digital and commercial stakeholders | M27: Validate India use case and request an appropriate business conversation | N27: Role verification and internal sponsorship required | O27: Planned
A28: OPP-023 | B28: ACC-023 | D28: Metropolis Healthcare | E28: Unassigned - contact research required | F28: Diagnostics AI; commercial evidence | G28: ₹10L–₹40L | H28: Research | I28: 15 | J28: 46359 | K28: Internal build; existing data vendors | L28: Map India medical, clinical, digital and commercial stakeholders | M28: Validate India use case and request an appropriate business conversation | N28: Role verification and internal sponsorship required | O28: Planned
A29: OPP-024 | B29: ACC-024 | D29: Dr. Lal PathLabs | E29: Unassigned - contact research required | F29: Diagnostics AI; workflow | G29: ₹10L–₹40L | H29: Research | I29: 15 | J29: 46360 | K29: Internal build; existing data vendors | L29: Map India medical, clinical, digital and commercial stakeholders | M29: Validate India use case and request an appropriate business conversation | N29: Role verification and internal sponsorship required | O29: Planned
A30: OPP-025 | B30: ACC-025 | D30: Narayana Health | E30: Unassigned - contact research required | F30: Imaging AI; clinical workflow | G30: ₹10L–₹40L | H30: Research | I30: 15 | J30: 46361 | K30: Internal build; existing data vendors | L30: Map India medical, clinical, digital and commercial stakeholders | M30: Validate India use case and request an appropriate business conversation | N30: Role verification and internal sponsorship required | O30: Planned

Sheet Outreach & Activities
A1: Outreach & Activities
A2: Use approved business channels. Do not add scraped or inferred personal contact information.
A5: Date | B5: Activity type | C5: Owner | D5: Target contact ID | E5: Target contact | F5: Outcome | G5: Next action | H5: Next-action date | I5: Follow-up status | J5: Meeting notes / context | K5: Automated flag
A6: 46266 | B6: Research review | C6: Life Sciences BD - India | D6: CON-001 | E6: Dilip Shanghvi | F6: Role and source reviewed | G6: Verify relevance and approved contact channel | H6: 46296 | I6: Completed | J6: Use only approved business channels; no inferred email or personal profile URL. | K6: =IF(AND(J6<>"Completed",I6<TODAY()),"OVERDUE",IF(J6="Completed","Complete","Open")) -> Open
A7: 46267 | B7: India outreach preparation | C7: Life Sciences BD - India | D7: CON-002 | E7: Kirti Ganorkar | F7: Pending internal outreach approval | G7: Verify relevance and approved contact channel | H7: 46297 | I7: Follow-up Due | J7: Use only approved business channels; no inferred email or personal profile URL. | K7: =IF(AND(J7<>"Completed",I7<TODAY()),"OVERDUE",IF(J7="Completed","Complete","Open")) -> Open
A8: 46268 | B8: India outreach preparation | C8: Life Sciences BD - India | D8: CON-003 | E8: Aalok Shanghvi | F8: Pending internal outreach approval | G8: Verify relevance and approved contact channel | H8: 46298 | I8: Follow-up Due | J8: Use only approved business channels; no inferred email or personal profile URL. | K8: =IF(AND(J8<>"Completed",I8<TODAY()),"OVERDUE",IF(J8="Completed","Complete","Open")) -> Open
A9: 46269 | B9: Research review | C9: Life Sciences BD - India | D9: CON-004 | E9: Vidhi Shanghvi | F9: Role and source reviewed | G9: Verify relevance and approved contact channel | H9: 46299 | I9: Completed | J9: Use only approved business channels; no inferred email or personal profile URL. | K9: =IF(AND(J9<>"Completed",I9<TODAY()),"OVERDUE",IF(J9="Completed","Complete","Open")) -> Open
A10: 46270 | B10: India outreach preparation | C10: Life Sciences BD - India | D10: CON-005 | E10: Pawan Goenka | F10: Pending internal outreach approval | G10: Verify relevance and approved contact channel | H10: 46300 | I10: Follow-up Due | J10: Use only approved business channels; no inferred email or personal profile URL. | K10: =IF(AND(J10<>"Completed",I10<TODAY()),"OVERDUE",IF(J10="Completed","Complete","Open")) -> Open
A11: 46271 | B11: India outreach preparation | C11: Life Sciences BD - India | D11: CON-006 | E11: Gautam Doshi | F11: Pending internal outreach approval | G11: Verify relevance and approved contact channel | H11: 46301 | I11: Follow-up Due | J11: Use only approved business channels; no inferred email or personal profile URL. | K11: =IF(AND(J11<>"Completed",I11<TODAY()),"OVERDUE",IF(J11="Completed","Complete","Open")) -> Open
A12: 46272 | B12: Research review | C12: Life Sciences BD - India | D12: CON-007 | E12: Andreas Eugen Busch | F12: Role and source reviewed | G12: Verify relevance and approved contact channel | H12: 46302 | I12: Completed | J12: Use only approved business channels; no inferred email or personal profile URL. | K12: =IF(AND(J12<>"Completed",I12<TODAY()),"OVERDUE",IF(J12="Completed","Complete","Open")) -> Open
A13: 46273 | B13: India outreach preparation | C13: Life Sciences BD - India | D13: CON-008 | E13: Rolf Hoffmann | F13: Pending internal outreach approval | G13: Verify relevance and approved contact channel | H13: 46303 | I13: Follow-up Due | J13: Use only approved business channels; no inferred email or personal profile URL. | K13: =IF(AND(J13<>"Completed",I13<TODAY()),"OVERDUE",IF(J13="Completed","Complete","Open")) -> Open
A14: 46274 | B14: India outreach preparation | C14: Life Sciences BD - India | D14: CON-009 | E14: Satyavati Berera | F14: Pending internal outreach approval | G14: Verify relevance and approved contact channel | H14: 46304 | I14: Follow-up Due | J14: Use only approved business channels; no inferred email or personal profile URL. | K14: =IF(AND(J14<>"Completed",I14<TODAY()),"OVERDUE",IF(J14="Completed","Complete","Open")) -> Open
A15: 46275 | B15: Research review | C15: Life Sciences BD - India | D15: CON-010 | E15: Kalyanasundaram Subramanian | F15: Role and source reviewed | G15: Verify relevance and approved contact channel | H15: 46305 | I15: Completed | J15: Use only approved business channels; no inferred email or personal profile URL. | K15: =IF(AND(J15<>"Completed",I15<TODAY()),"OVERDUE",IF(J15="Completed","Complete","Open")) -> Open
A16: 46276 | B16: India outreach preparation | C16: Life Sciences BD - India | D16: CON-011 | E16: Jayashree Satagopan | F16: Pending internal outreach approval | G16: Verify relevance and approved contact channel | H16: 46306 | I16: Follow-up Due | J16: Use only approved business channels; no inferred email or personal profile URL. | K16: =IF(AND(J16<>"Completed",I16<TODAY()),"OVERDUE",IF(J16="Completed","Complete","Open")) -> Open
A17: 46277 | B17: India outreach preparation | C17: Life Sciences BD - India | D17: CON-012 | E17: Anoop Deshpande | F17: Pending internal outreach approval | G17: Verify relevance and approved contact channel | H17: 46307 | I17: Follow-up Due | J17: Use only approved business channels; no inferred email or personal profile URL. | K17: =IF(AND(J17<>"Completed",I17<TODAY()),"OVERDUE",IF(J17="Completed","Complete","Open")) -> Open
... A35: 46295 | B35: India outreach preparation | C35: Life Sciences BD - India | D35: CON-030 | E35: Saugata Gupta | F35: Pending internal outreach approval | G35: Verify relevance and approved contact channel | H35: 46325 | I35: Follow-up Due | J35: Use only approved business channels; no inferred email or personal profile URL. | K35: =IF(AND(J35<>"Completed",I35<TODAY()),"OVERDUE",IF(J35="Completed","Complete","Open")) -> Open

Sheet Research Sources
A1: Research Sources
A2: Citation ledger. Every researched account and contact is represented below.
A5: Source URL | B5: Source type | C5: Linked account ID | D5: Linked contact ID | E5: Extracted information | F5: Date accessed | G5: Verification / confidence
A6: https://sunpharma.com/board-of-directors/ | B6: Official company / leadership page | C6: ACC-001 | D6: Sun Pharmaceutical Industries | E6: India account profile and/or leadership source for Sun Pharmaceutical Industries. | F6: 46295 | G6: Official source / high
A7: https://api.drreddys.com/pt-pt/events/cphi-india-2025 | B7: Official company / leadership page | C7: ACC-002 | D7: Dr. Reddy’s Laboratories | E7: India account profile and/or leadership source for Dr. Reddy’s Laboratories. | F7: 46295 | G7: Official source / high
A8: https://www.cipla.com/node/713474 | B8: Official company / leadership page | C8: ACC-003 | D8: Cipla | E8: India account profile and/or leadership source for Cipla. | F8: 46295 | G8: Official source / high
A9: https://www.biocon.com/about-us/executive-committee/ | B9: Official company / leadership page | C9: ACC-004 | D9: Biocon | E9: India account profile and/or leadership source for Biocon. | F9: 46295 | G9: Official source / high
A10: https://lupin.com/about-us/leadership | B10: Official company / leadership page | C10: ACC-005 | D10: Lupin | E10: India account profile and/or leadership source for Lupin. | F10: 46295 | G10: Official source / high
A11: https://www.aurobindo.com/about-us/management/board-of-directors | B11: Official company / leadership page | C11: ACC-006 | D11: Aurobindo Pharma | E11: India account profile and/or leadership source for Aurobindo Pharma. | F11: 46295 | G11: Official source / high
A12: https://alembicpharmaceuticals.com/shareholder-information | B12: Official company / leadership page | C12: ACC-007 | D12: Alembic Pharmaceuticals | E12: India account profile and/or leadership source for Alembic Pharmaceuticals. | F12: 46295 | G12: Official source / high
A13: https://india-pharma.gsk.com/en-in/company/board-of-directors-and-india-leadership-team/ | B13: Official company / leadership page | C13: ACC-008 | D13: GSK India | E13: India account profile and/or leadership source for GSK India. | F13: 46295 | G13: Official source / high
A14: https://www.zyduslife.com/investor/admin/uploads/14/2/2024-2025.pdf | B14: Official company / leadership page | C14: ACC-009 | D14: Zydus Lifesciences | E14: India account profile and/or leadership source for Zydus Lifesciences. | F14: 46295 | G14: Official source / high
A15: https://www.torrentpharma.com/investors/corporate-governance/board-of-directors/ | B15: Official company / leadership page | C15: ACC-010 | D15: Torrent Pharmaceuticals | E15: India account profile and/or leadership source for Torrent Pharmaceuticals. | F15: 46295 | G15: Official source / high
A16: https://www.mankindpharma.com/about-us/board-of-directors | B16: Official company / leadership page | C16: ACC-011 | D16: Mankind Pharma | E16: India account profile and/or leadership source for Mankind Pharma. | F16: 46295 | G16: Official source / high
A17: https://www.emcure.com/about-us/leadership/ | B17: Official company / leadership page | C17: ACC-012 | D17: Emcure Pharmaceuticals | E17: India account profile and/or leadership source for Emcure Pharmaceuticals. | F17: 46295 | G17: Official source / high
... A130: https://www.emcure.com/about-us/leadership/ | B130: Official company leadership page | C130: ACC-012 | D130: CON-100 | E130: Namita Thapar — Executive Director. | F130: 46295 | G130: Unverified; recheck official company source

Sheet How to Use
A1: How to Use
A2: Workflow, governance and data-quality rules.
A5: Workflow step | B5: Guidance
A6: 1. Add or update an account | B6: Create a unique Account ID for an India-relevant company. Select sector, tier, India owner, and relationship status from the dropdowns. Add a current official source URL and research date.
A7: 2. Add a contact | B7: Use public professional information only. Add a personal profile URL only if you verified it. Never infer email formats, phone numbers, job titles, or LinkedIn URLs.
A8: 3. Cite the source | B8: Add a Research Sources row for every research-backed account/contact update. Mark unverified information explicitly.
A9: 4. Qualify the opportunity | B9: Create an opportunity only after an India-specific use case is identified. INR value bands and close dates are planning inputs, not committed revenue.
A10: 5. Log outreach | B10: Record approved outreach, next action, and deadline in Outreach & Activities. The Automated flag detects overdue items.
A11: 6. Weekly hygiene | B11: Review overdue flags, sources older than 90 days, account coverage, unverified roles, and India owner assignment. Re-verify changing titles before outreach.
A12: Data-quality rule | B12: “Verified - official source” means title/name was seen on the linked official company page on the stated date. It does not confirm a direct relationship or outreach permission.
A13: Privacy / compliance | B13: This workbook intentionally omits inferred or scraped personal contact details. Use approved company channels and your organization’s privacy/compliance policies before outreach.

Sheet Lists
A1: Controlled Lists
A2: Update list values only with CRM governance approval.
A5: Sector | B5: Tier | C5: Stage | D5: Seniority | E5: Owner | F5: Activity Status | G5: Relationship Status | H5: Function | I5: Influence
A6: Pharma | B6: Tier 1 | C6: Research | D6: C-suite | E6: Unassigned | F6: Planned | G6: Prospect | H6: Executive Leadership | I6: Economic Buyer
A7: Biotech | B7: Tier 2 | C7: Qualified | D7: EVP/SVP | E7: Life Sciences BD - Global | F7: Completed | G7: Warm | H7: R&D / Clinical Development | I7: Champion
A8: Diagnostics | B8: Tier 3 | C8: Discovery | D8: VP | E8: Life Sciences BD - India | F8: Follow-up Due | G8: Active Dialogue | H8: Medical Affairs | I8: Technical Evaluator
A9: Imaging & MedTech | C9: Proposal | D9: Director | E9: Strategic Partnerships | F9: Overdue | G9: Partner | H9: Digital / Data / AI | I9: End User
A10: Digital Health | C10: Negotiation | D10: Global Head | E10: Clinical Solutions | F10: On Hold | G10: Dormant | H10: Diagnostics / Imaging | I10: Blocker
A11: Clinical Research | C11: Closed Won | D11: Business Unit Head | H11: Commercial / Market Access
C12: Closed Lost | H12: Corporate Development
H13: Operations / Supply
